matrix_saml_strip_hostname/__init__.py
matrix_saml_strip_hostname/mapping_providers.py
matrix_saml_strip_hostname-0.2.2.dist-info/LICENSE
matrix_saml_strip_hostname-0.2.2.dist-info/WHEEL
matrix_saml_strip_hostname-0.2.2.dist-info/METADATA
matrix_saml_strip_hostname-0.2.2.dist-info/RECORD
