Metadata-Version: 2.1
Name: matrix-saml-strip-hostname
Version: 0.2.2
Summary: SAML mapping provider to strip hostnames from mxids
Author-email: Sylvain Fankhauser <sephi@fhtagn.top>
Requires-Python: >=3.7
